slenderql/__init__.py
slenderql/db.py
slenderql/py.typed
slenderql/repository.py
slenderql-0.1.6.dist-info/METADATA
slenderql-0.1.6.dist-info/WHEEL
slenderql-0.1.6.dist-info/licenses/LICENSE
slenderql-0.1.6.dist-info/RECORD
