Metadata-Version: 2.4
Name: SlenderQL
Version: 0.1.6
Summary: Missing library for working with raw SQL in Python/psycopg
Author-email: Aleksandr Gridnev <gridnev.alexandr@gmail.com>
License-File: LICENSE
Requires-Python: >=3.12
Requires-Dist: psycopg[binary,pool]>=3.2.7
Requires-Dist: pydantic>=2.11.4
Requires-Dist: requests>2.32.4
Requires-Dist: sentry-sdk[fastapi]>=2.27.0
Requires-Dist: starlette>=0.47.2
Requires-Dist: urllib3>=2.5.0
